README.rst
setup.py
multiprocessframe/__init__.py
multiprocessframe/multiProcess.py
multiprocessframe/multiProcessWorkFrame.py
multiprocessframe.egg-info/PKG-INFO
multiprocessframe.egg-info/SOURCES.txt
multiprocessframe.egg-info/dependency_links.txt
multiprocessframe.egg-info/top_level.txt
multiprocessframe.egg-info/zip-safe