Metadata-Version: 1.1
Name: multiprocessframe
Version: 0.0.1
Summary: A multiprocess frame to deal with a series tasks easily.
Home-page: http://blog.sjwjiawei.cn/
Author: Shen jiawei
Author-email: 419910650@qq.com
License: MIT
Keywords: multiprocess
Platform: UNKNOWN
Classifier: License :: OSI Approved :: MIT License
Classifier: Programming Language :: Python
Classifier: Intended Audience :: Developers
Classifier: Operating System :: POSIX :: Linux
